_examples/__init__.py
examples/__init__.py
regtools/__init__.py
regtools/args.py
regtools/chooser.py
regtools/controls.py
regtools/dataprep.py
regtools/differenced.py
regtools/ext_statsmodels.py
regtools/interact.py
regtools/iter.py
regtools/models.py
regtools/order.py
regtools/quantile.py
regtools/reg.py
regtools/regtypes.py
regtools/select.py
regtools/tools.py
regtools/cluster/__init__.py
regtools/cluster/output.py
regtools/fe/__init__.py
regtools/fe/dataprep.py
regtools/fe/output.py
regtools/fe/tools.py
regtools/hypothesis/__init__.py
regtools/hypothesis/lincom.py
regtools/lag/__init__.py
regtools/lag/create.py
regtools/lag/main.py
regtools/lag/plot.py
regtools/lag/remove.py
regtools/linmodels/__init__.py
regtools/linmodels/reg.py
regtools/linmodels/bindings/__init__.py
regtools/linmodels/bindings/fe.py
regtools/linmodels/bindings/fit.py
regtools/linmodels/bindings/input.py
regtools/linmodels/bindings/modelstr.py
regtools/linmodels/bindings/result.py
regtools/summarize/__init__.py
regtools/summarize/split.py
regtools/summarize/tstat.py
regtools/summarize/yesno.py
tests/__init__.py
tests/test_lag_create.py
tests/test_reg.py
regtools-0.1.4.dist-info/LICENSE.md
regtools-0.1.4.dist-info/METADATA
regtools-0.1.4.dist-info/WHEEL
regtools-0.1.4.dist-info/entry_points.txt
regtools-0.1.4.dist-info/top_level.txt
regtools-0.1.4.dist-info/RECORD
